{
  "$schema": "../chains.schema.json",
  "name": "Everstake",
  "chains": [
    {
      "name": "theta",
      "address": "cosmosvaloper1tflk30mq5vgqjdly92kkhhq3raev2hnz6eete3",
      "restake": {
        "address": "cosmos1g3laz9zpgy8x4k3gdkydf4umnepaug4wh88g0z",
        "run_time": [
          "09:00",
          "21:00"
        ],
        "minimum_reward": 5000
      }
    },
	  
    {
      "name": "acrechain",
      "address": "acrevaloper1rvrecs7f3pdlplq75nhqtmegruthhsn8xqjr0z",
      "restake": {
        "address": "acre186u3vpyt6zxvyk7a4yv7h7cggtnexn93sdun9d",
        "run_time": [
          "09:00",
          "21:00"
	],
        "minimum_reward": 100000000000000000
      }
    }, 
	  
    {
      "name": "assetmantle",
      "address": "mantlevaloper1jdu6zx8wpkwcwnj9dg3nslq7m66nfyh9uskw5s",
      "restake": {
        "address": "mantle1g3laz9zpgy8x4k3gdkydf4umnepaug4wfrudsg",
        "run_time": [
          "09:00",
          "21:00"
	],
        "minimum_reward": 10000
      }
    },
	  
    {
      "name": "cosmoshub",
      "address": "cosmosvaloper1tflk30mq5vgqjdly92kkhhq3raev2hnz6eete3",
      "restake": {
        "address": "cosmos1g3laz9zpgy8x4k3gdkydf4umnepaug4wh88g0z",
        "run_time": [
          "09:00",
          "21:00"
	],
        "minimum_reward": 10000
      }
    },	  
    
    {
      "name": "injective",
      "address": "injvaloper134dct56cq5v7uerxcy2cn4m06mqf4dxrlgpp24",
      "restake": {
        "address": "inj186u3vpyt6zxvyk7a4yv7h7cggtnexn93q8n5gc",
        "run_time": [
	  "09:00", 
	  "21:00"
	],
        "minimum_reward": 100000000000000
      }
    },
	
    {
      "name": "stride",
      "address": "stridevaloper19nktvlnhd7j2tsyt97jyfnv3kdemx8cqx25ng7",
      "restake": {
        "address": "stride1g3laz9zpgy8x4k3gdkydf4umnepaug4w5v85mw",
        "run_time": [
	  "09:00", 
	  "21:00"
	],
        "minimum_reward": 1000
      }
    }
  ]
}
